setup.py
tests/__init__.py
tests/test_client.py
tests/test_extract_message.py
tests/test_main.py
tests/test_stream.py
tests/test_syslog.py
tests/test_tasks.py
tsuru_unit_agent/__init__.py
tsuru_unit_agent/client.py
tsuru_unit_agent/heartbeat.py
tsuru_unit_agent/main.py
tsuru_unit_agent/stream.py
tsuru_unit_agent/syslog.py
tsuru_unit_agent/tasks.py
tsuru_unit_agent.egg-info/PKG-INFO
tsuru_unit_agent.egg-info/SOURCES.txt
tsuru_unit_agent.egg-info/dependency_links.txt
tsuru_unit_agent.egg-info/entry_points.txt
tsuru_unit_agent.egg-info/requires.txt
tsuru_unit_agent.egg-info/top_level.txt