Metadata-Version: 1.0
Name: tsuru-unit-agent
Version: 0.4.3
Summary: Tsuru unit agent.
Home-page: https://github.com/tsuru/tsuru-unit-agent
Author: tsuru
Author-email: tsuru@corp.globo.com
License: UNKNOWN
Platform: UNKNOWN
